yadisk/__init__.py
yadisk/_async_client.py
yadisk/_async_client.pyi
yadisk/_async_session.py
yadisk/_client.py
yadisk/_client.pyi
yadisk/_client_common.py
yadisk/_common.py
yadisk/_import_session.py
yadisk/_session.py
yadisk/_typing_compat.py
yadisk/exceptions.py
yadisk/py.typed
yadisk/settings.py
yadisk/types.py
yadisk/utils.py
yadisk/_api/__init__.py
yadisk/_api/api_request.py
yadisk/_api/auth.py
yadisk/_api/disk.py
yadisk/_api/operations.py
yadisk/_api/resources.py
yadisk/objects/__init__.py
yadisk/objects/_auth.py
yadisk/objects/_disk.py
yadisk/objects/_error_object.py
yadisk/objects/_link_object.py
yadisk/objects/_operations.py
yadisk/objects/_operations.pyi
yadisk/objects/_resources.py
yadisk/objects/_resources.pyi
yadisk/objects/_yadisk_object.py
yadisk/sessions/__init__.py
yadisk/sessions/_httpx_common.py
yadisk/sessions/aiohttp_session.py
yadisk/sessions/async_httpx_session.py
yadisk/sessions/httpx_session.py
yadisk/sessions/pycurl_session.py
yadisk/sessions/requests_session.py
yadisk-3.1.0.dist-info/COPYING
yadisk-3.1.0.dist-info/COPYING.lesser
yadisk-3.1.0.dist-info/METADATA
yadisk-3.1.0.dist-info/WHEEL
yadisk-3.1.0.dist-info/top_level.txt
yadisk-3.1.0.dist-info/RECORD
