Metadata-Version: 2.1
Name: yadisk
Version: 3.1.0
Summary: Библиотека-клиент REST API Яндекс.Диска / Yandex.Disk REST API client library
Author-email: Ivan Konovalov <ivknv0@gmail.com>
License: LGPLv3
Project-URL: Source code, https://github.com/ivknv/yadisk
Project-URL: Documentation (EN), https://yadisk.readthedocs.io/en/latest
Project-URL: Documentation (RU), https://yadisk.readthedocs.io/ru/latest
Project-URL: Bug tracker, https://github.com/ivknv/yadisk/issues
Keywords: yandex.disk,yandex,rest
Classifier: Development Status :: 5 - Production/Stable
Classifier: Intended Audience :: Developers
Classifier: License :: OSI Approved :: GNU Lesser General Public License v3 (LGPLv3)
Classifier: License :: OSI Approved :: GNU Lesser General Public License v3 or later (LGPLv3+)
Classifier: Programming Language :: Python
Classifier: Programming Language :: Python :: 3
Classifier: Programming Language :: Python :: 3 :: Only
Classifier: Programming Language :: Python :: 3.8
Classifier: Programming Language :: Python :: 3.9
Classifier: Programming Language :: Python :: 3.10
Classifier: Programming Language :: Python :: 3.11
Classifier: Programming Language :: Python :: 3.12
Classifier: Operating System :: OS Independent
Classifier: Topic :: Internet
Classifier: Topic :: Software Development :: Libraries
Classifier: Topic :: Software Development :: Libraries :: Python Modules
Requires-Python: >=3.8
License-File: COPYING
License-File: COPYING.lesser
Requires-Dist: typing_extensions; python_version < "3.10"
Provides-Extra: sync-defaults
Requires-Dist: requests; extra == "sync-defaults"
Provides-Extra: async-defaults
Requires-Dist: aiofiles; extra == "async-defaults"
Requires-Dist: httpx; extra == "async-defaults"
Provides-Extra: async-files
Requires-Dist: aiofiles; extra == "async-files"
Provides-Extra: aiohttp
Requires-Dist: aiohttp; extra == "aiohttp"
Provides-Extra: httpx
Requires-Dist: httpx; extra == "httpx"
Provides-Extra: pycurl
Requires-Dist: pycurl; extra == "pycurl"
Provides-Extra: requests
Requires-Dist: requests; extra == "requests"
